[
      {
          "id": "P001",
          "name": "Andrés",
          "lastName": "Zelada",
          "alias": "Vimes",
          "image": "vimes.jpg",
          "bio": "vimes.txt"
      },
      {
          "id": "P002",
          "name": "Laura",
          "lastName": "Tárraga",
          "image": "Laura-Tarraga-Hispacon.png",
          "bio": "lauratarraga.txt"
      },
      {
          "id": "P003",
          "name": "Adella",
          "lastName": "Brac",
          "image": "adella-brac.jpg",
          "bio": "adellabrac.txt"
      },
      {
          "id": "P004",
          "name": "Roberto",
          "lastName": "López-Herrero",
          "image": "RLH_400x400.jpg",
          "bio": "rlh.txt"
      },
      {
          "id": "P005",
          "name": "Seanan",
          "lastName": "McGuire",
          "image": "Seanan1.jpg",
          "bio": "mcguire.txt"
      },
      {
          "id": "P006",
          "name": "Celia",
          "lastName": "Arias Fernández",
          "image": "Celia-Arias-Fernandez.png",
          "bio": "celiaarias.txt"
      },
      {
          "id": "P007",
          "name": "Juan",
          "lastName": "Pascual Martínez",
          "image": "JuanPascual.jpg",
          "bio": "jpascual.txt"
      },
      {
          "id": "P008",
          "name": "Diego",
          "lastName": "Salcedo",
          "image": "DiegoSalcedo.jpg",
          "bio": "dsalcedo.txt"
      },
      {
          "id": "P009",
          "name": "Héctor",
          "lastName": "Vielva",
          "image": "HectorVielva.jpg",
          "bio": "hvielva.txt"
      },
      {
          "id": "P010",
          "name": "Javier",
          "lastName": "Font",
          "image": "JavierFont.jpg",
          "bio": "jfont.txt"
      },
      {
          "id": "P011",
          "name": "Laura S",
          "lastName": "Maquilón",
          "image": "LauraMaquilon.jpg",
          "bio": "sierpe.txt"
      },
      {
          "id": "P012",
          "name": "Marco",
          "lastName": "Granado",
          "image": "MarcoGranado.jpeg",
          "bio": "mgranado.txt"
      },
      {
          "id": "P013",
          "name": "Néstor",
          "lastName": "Román",
          "image": "NestorRoman.png",
          "bio": "nroman.txt"
      },
      {
          "id": "P014",
          "name": "Sara",
          "lastName": "Sacristán",
          "image": "SARA_SACRISTAN.jpg",
          "bio": "ssacristan.txt"
      },
      {
          "id": "P015",
          "name": "Claudio",
          "lastName": "Amodeo",
          "image": "camodeo.jpg",
          "bio": "camodeo.txt"
      },
      {
          "id": "P016",
          "name": "Alberto",
          "lastName": "Sepúlveda",
          "bio": "asepulveda.txt"
      },
      {
          "id": "P017",
          "name": "Eva",
          "lastName": "García Guerrero",
          "image": "egguerrero.jpg",
          "bio": "egarciag.txt"
      },
      {
          "id": "P018",
          "name": "Ibán",
          "lastName": "Sánchez",
          "image": "isanchez.jpg",
          "bio": "isanchez.txt"
      },
      {
          "id": "P020",
          "name": "José Ángel",
          "lastName": "Menéndez Lucas",
          "image": "jamenendez.png",
          "bio": "jamenendez.txt"
      },
      {
          "id": "P021",
          "name": "Yaiza",
          "lastName": "Carrasco",
          "image": "Foto_YaizaCarrasco.jpg",
          "bio": "ycarrasco.txt"
      },
      {
          "id": "P022",
          "name": "Manuel",
          "lastName": "Ortiz",
          "image": "Foto_ManuelOrtiz.jpeg",
          "bio": "mortiz.txt"
      },
      {
          "id": "P023",
          "name": "Aitor",
          "lastName": "Díaz",
          "image": "Foto_AitorDiaz.jpg",
          "bio": "aitordiaz.txt"
      },
      {
          "id": "P024",
          "name": "Irene",
          "lastName": "Robles",
          "image": "Foto_IreneRobles.jpg",
          "bio": "irobles.txt"
      },
      {
          "id": "P025",
          "name": "Andrea",
          "lastName": "Penalva",
          "image": "Foto_AndreaPenalva.jpg",
          "bio": "apenalva.txt"
      },
      {
          "id": "P026",
          "name": "Virginia",
          "lastName": "Buedo",
          "image": "Foto_VirginiaBuedo.jpg",
          "bio": "vbuedo.txt"
      },
      {
          "id": "P027",
          "name": "Viriato",
          "lastName": "Valdés Valiña",
          "image": "vvaldes.jpg",
          "bio": "vvaldes.txt"
      },
      {
          "id": "P028",
          "name": "Reyes",
          "lastName": "Abades",
          "image": "rabades.png",
          "bio": "rabades.txt"
      },
      {
          "id": "P029",
          "name": "Xurxo",
          "lastName": "Diz Pico",
          "image": "xdiz.jpg",
          "bio": "xdiz.txt"
      },
      {
          "id": "P030",
          "name": "Xabier",
          "lastName": "Landabidea Urresti",
          "image": "xlandabidea.jpg",
          "bio": "xlandabidea.txt"
      },
      {
          "id": "P031",
          "name": "Isabel",
          "lastName": "Clemente Burcio",
          "image": "iclemente.jpg",
          "bio": "iclemente.txt"
      },
      {
          "id": "P032",
          "name": "Álex",
          "lastName": "Sebastián",
          "bio": "asebastian.txt"
      },
      {
          "id": "P033",
          "name": "Almijara",
          "lastName": "Barbero Carvajal",
          "bio": "abarbero.txt"
      },
      {
          "id": "P034",
          "alias": "Alystrin",
          "image": "Alystrin.jpg",
          "bio": "alystrin.txt"
      },
      {
          "id": "P035",
          "name": "Ander",
          "lastName": "Mombiela",
          "bio": "amombiela.txt"
      },
      {
          "id": "P036",
          "name": "Ángel",
          "lastName": "Vallecillo",
          "bio": "avallecillo.txt"
      },
      {
          "id": "P037",
          "alias": "Azka",
          "image": "azka.jpg",
          "bio": "azka.txt"
      },
      {
          "id": "P038",
          "name": "Camila",
          "lastName": "Almendra",
          "image": "calmendra.jpg",
          "bio": "calmendra.txt"
      },
      {
          "id": "P039",
          "name": "Claudia",
          "lastName": "Fontana",
          "image": "cfontana.jpg",
          "bio": "cfontana.txt"
      },
      {
          "id": "P040",
          "name": "Cristina del",
          "lastName": "Toro Tomás",
          "image": "ctoro.jpg",
          "bio": "ctoro.txt"
      },
      {
          "id": "P041",
          "name": "Cristina",
          "lastName": "Jurado",
          "image": "oughyeagh.jpg",
          "bio": "oughyeagh.txt"
      },
      {
          "id": "P042",
          "name": "Cristina",
          "lastName": "Martín de Francisco",
          "image": "cmartin.png",
          "bio": "cmartin.txt"
      },
      {
          "id": "P043",
          "name": "María José",
          "lastName": "Sánchez",
          "bio": "cprieto.txt"
      },
      {
          "id": "P044",
          "name": "Dana",
          "lastName": "Lima",
          "bio": "dlima.txt"
      },
      {
          "id": "P045",
          "alias": "Darkor_LF",
          "image": "darkor.jpg",
          "bio": "darkor.txt"
      },
      {
          "id": "P046",
          "name": "Elaine",
          "lastName": "Vilar Madruga",
          "image": "evilar.png",
          "bio": "evilar.txt"
      },
      {
          "id": "P047",
          "name": "Francis",
          "lastName": "Novoa",
          "bio": "fnovoa.txt"
      },
      {
          "id": "P048",
          "name": "Francisco",
          "lastName": "Jota-Pérez",
          "bio": "fjota.txt"
      },
      {
          "id": "P049",
          "name": "Francisco",
          "lastName": "Tapia-Fuentes",
          "bio": "ftapia.txt"
      },
      {
          "id": "P050",
          "name": "Ismael F.",
          "lastName": "Cabeza",
          "image": "icabeza.jpg",
          "bio": "icabeza.txt"
      },
      {
          "id": "P051",
          "name": "Jorge",
          "lastName": "Salvador Galindo",
          "image": "jsalvador.jpg",
          "bio": "jsalvador.txt"
      },
      {
          "id": "P052",
          "name": "José Ángel",
          "lastName": "Conde",
          "image": "jaconde.jpg",
          "bio": "jaconde.txt"
      },
      {
          "id": "P053",
          "name": "José Luis",
          "lastName": "Pastor Diez",
          "bio": "jlpastor.txt"
      },
      {
          "id": "P054",
          "name": "José Manuel",
          "lastName": "Cárdenas",
          "image": "Jose-Cardenas.jpg",
          "bio": "jmcardenas.txt"
      },
      {
          "id": "P055",
          "name": "José R.",
          "lastName": "Montejano",
          "image": "Jose-Montejano.jpg",
          "bio": "jmontejano.txt"
      },
      {
          "id": "P056",
          "name": "Josué",
          "lastName": "Ramos",
          "image": "jramos.jpeg",
          "bio": "jramos.txt"
      },
      {
          "id": "P057",
          "name": "Laura",
          "lastName": "Ponce",
          "image": "lponce.jpg",
          "bio": "lponce.txt"
      },
      {
          "id": "P058",
          "name": "Libia",
          "lastName": "Brenda",
          "image": "lbrenda.jpg",
          "bio": "lbrenda.txt"
      },
      {
          "id": "P059",
          "name": "Loreto",
          "lastName": "ML",
          "image": "lml.jpg",
          "bio": "lml.txt"
      },
      {
          "id": "P060",
          "name": "Lou W.",
          "lastName": "Morrison",
          "image": "lmorrison.jpg",
          "bio": "lmorrison.txt"
      },
      {
          "id": "P061",
          "name": "Lucía G.",
          "lastName": "Sobrado",
          "image": "lsobrado.jpg",
          "bio": "lsobrado.txt"
      },
      {
          "id": "P062",
          "name": "Luis",
          "lastName": "Gómez García",
          "image": "lgomez.png",
          "bio": "lgomez.txt"
      },
      {
          "id": "P063",
          "name": "Luisa",
          "lastName": "Oliva",
          "image": "loliva.png",
          "bio": "loliva.txt"
      },
      {
          "id": "P064",
          "name": "Maielis",
          "lastName": "González",
          "image": "maielis.jpg",
          "bio": "maielis.txt"
      },
      {
          "id": "P065",
          "name": "Manuel",
          "lastName": "Gutiérrez",
          "image": "mgutierrez.jpg",
          "bio": "mgutierrez.txt"
      },
      {
          "id": "P066",
          "name": "Meren",
          "lastName": "Plath",
          "image": "mplath.png",
          "bio": "mplath.txt"
      },
      {
          "id": "P067",
          "lastName": "Mirabilia Libros",
          "image": "mirabilia.jpg",
          "bio": "mirabilia.txt"
      },
      {
          "id": "P068",
          "name": "Nicole",
          "lastName": "Fadellin",
          "image": "nfadellin.jpg",
          "bio": "nfadellin.txt"
      },
      {
          "id": "P069",
          "name": "Óscar",
          "lastName": "Navas",
          "image": "onavas.png",
          "bio": "onavas.txt"
      },
      {
          "id": "P070",
          "name": "Rafael",
          "lastName": "Acevedo",
          "image": "racevedo.jpg",
          "bio": "racevedo.txt"
      },
      {
          "id": "P071",
          "name": "Ramiro",
          "lastName": "Sanchiz",
          "image": "rsanchiz.jpg",
          "bio": "rsanchiz.txt"
      },
      {
          "id": "P072",
          "name": "Rodrigo",
          "lastName": "Bastidas Pérez",
          "image": "rbastidas.jpg",
          "bio": "rbastidas.txt"
      },
      {
          "id": "P073",
          "name": "Sergio S.",
          "lastName": "Morán",
          "bio": "smoran.txt"
      },
      {
          "id": "P074",
          "name": "Sheila",
          "lastName": "Carnero",
          "image": "scarnero.jpg",
          "bio": "scarnero.txt"
      },
      {
          "id": "P075",
          "name": "Silvia",
          "lastName": "Moreno-García",
          "image": "smoreno.jpg",
          "bio": "smoreno.txt"
      },
      {
          "id": "P076",
          "name": "Tomás",
          "lastName": "Apan",
          "image": "Tomas_Apan.jpeg",
          "bio": "tapan.txt"
      },
      {
          "id": "P077",
          "name": "Yakamí",
          "lastName": "Machado",
          "image": "ymachado.png",
          "bio": "ymachado.txt"
      },
      {
          "id": "P078",
          "name": "Yasmin S.",
          "lastName": "Portales-Machado",
          "image": "yportales.jpg",
          "bio": "yportales.txt"
      },
      {
          "id": "P079",
          "name": "Adriana",
          "lastName": "Bañares",
          "image": "abanares.jpg",
          "bio": "abanares.txt"
      },
      {
          "id": "P080",
          "alias": "Akusokozan",
          "image": "Akusokozan.jpg",
          "bio": "akusokozan.txt"
      },
      {
          "id": "P081",
          "name": "Alfred",
          "lastName": "Almasy",
          "image": "aalmasy.jpg",
          "bio": "almasy.txt"
      },
      {
          "id": "P082",
          "name": "Aritz P.",
          "lastName": "Berra",
          "image": "aritz.jpeg",
          "bio": "aberra.txt"
      },
      {
          "id": "P083",
          "name": "Carla",
          "lastName": "Plumed",
          "image": "cplumed.jpeg",
          "bio": "cplumed.txt"
      },
      {
          "id": "P084",
          "name": "Jo",
          "lastName": "Walton",
          "image": "jwalton.jpg",
          "bio": "jwalton.txt"
      },
      {
          "id": "P085",
          "name": "Laura",
          "lastName": "Arenas",
          "image": "larenas.jpg",
          "bio": "larenas.txt"
      },
      {
          "id": "P086",
          "name": "Libertad",
          "lastName": "Delgado",
          "alias": "LiberLibelula",
          "image": "ldelgado.jpg",
          "bio": "ldelgado.txt"
      },
      {
          "id": "P087",
          "name": "Luis Alberto",
          "lastName": "Henríquez Hernández",
          "bio": "lahenriquez.txt"
      },
      {
          "id": "P088",
          "name": "Caryanna",
          "lastName": "Reuven",
          "image": "creuven.jpg",
          "bio": "creuven.txt"
      },
      {
          "id": "P089",
          "name": "Adrián",
          "lastName": "Díez Ramos",
          "image": "adiez.png",
          "bio": "adiez.txt"
      },
      {
          "id": "P090",
          "name": "Toñi",
          "lastName": "Gil",
          "alias": "Blueberrymess",
          "image": "tgil.png",
          "bio": "tgil.txt"
      },
      {
          "id": "P091",
          "alias": "El Bardo Chillón",
          "image": "bardo.png",
          "bio": "bardo.txt"
      },
      {
          "id": "P092",
          "name": "Alberto",
          "lastName": "Seijo",
          "image": "aseijo.png",
          "bio": "aseijo.txt"
      },
      {
          "id": "P093",
          "name": "Luis",
          "lastName": "Endera",
          "image": "lendera.jpg",
          "bio": "lendera.txt"
      },
      {
          "id": "P094",
          "name": "Mónica",
          "lastName": "Sanz",
          "image": "jsalleres.jpg",
          "bio": "jsalleres.txt"
      },
      {
          "id": "P095",
          "lastName": "Ponce",
          "image": "DamianGPonce.jpg",
          "bio": "damiwan.txt"
      },
      {
          "id": "P096",
          "name": "Rosa",
          "lastName": "Soria",
          "image": "RosaSoria.jpg",
          "bio": "rsoria.txt"
      },
      {
          "id": "P097",
          "name": "Isabel",
          "lastName": "Pedrero",
          "image": "ipedrero.jpeg",
          "bio": "ipedrero.txt"
      },
      {
          "id": "P098",
          "name": "Ana",
          "lastName": "Saiz",
          "image": "asaiz.jpg",
          "bio": "asaiz.txt"
      },
      {
          "id": "P099",
          "name": "Penélope",
          "lastName": "Fernández",
          "image": "pfernandez.jpg",
          "bio": "pfernandez.txt"
      },
      {
          "id": "P100",
          "name": "Rafa C.",
          "lastName": "Bachiller",
          "image": "rbachiller.jpg",
          "bio": "rbachiller.txt"
      },
      {
          "id": "P101",
          "name": "Raquel S.",
          "lastName": "Valle",
          "image": "rvalle.jpg",
          "bio": "rvalle.txt"
      },
      {
          "id": "P102",
          "name": "Marta Inés",
          "lastName": "Rodríguez",
          "image": "mrodriguez.jpg",
          "bio": "mrodriguez.txt"
      },
      {
          "id": "P103",
          "name": "Sofía",
          "lastName": "Rhei",
          "image": "srhei.jpg",
          "bio": "srhei.txt"
      },
      {
          "id": "P104",
          "name": "Sònia",
          "lastName": "Boj",
          "image": "sboj.jpg",
          "bio": "sboj.txt"
      },
      {
          "id": "P105",
          "name": "Elena",
          "lastName": "Bartomeu",
          "image": "ebartomeu.png",
          "bio": "ebartomeu.txt"
      },
      {
          "id": "P106",
          "name": "Carlos",
          "lastName": "Pitillas Salvá",
          "image": "cpitillas.jpg"
      },
      {
          "id": "P107",
          "name": "Ferki",
          "lastName": "López",
          "image": "ferki.jpg"
      },
      {
          "id": "P108",
          "name": "Ismael",
          "lastName": "Martínez Biurrun",
          "image": "imbiurrun.jpg"
      },
      {
          "id": "P109",
          "name": "Lorena",
          "lastName": "Gil Rey",
          "image": "lgil.png"
      },
      {
          "id": "P110",
          "name": "Conchi",
          "lastName": "Regueiro"
      },
      {
          "id": "P111",
          "name": "Victoria",
          "lastName": "Janeiro"
      },
      {
          "id": "P112",
          "name": "Borja",
          "lastName": "Tosar"
      },
      {
          "id": "P113",
          "name": "Victoria",
          "lastName": "Álvarez"
      },
      {
          "id": "P114",
          "name": "Ana",
          "lastName": "Roux"
      },
      {
          "id": "P115",
          "name": "Kate",
          "lastName": "Lynnon"
      },
      {
          "id": "P116",
          "name": "Beatriz",
          "lastName": "García"
      },
      {
          "id": "P117",
          "name": "Isa J.",
          "lastName": "González",
          "image": "janis.png",
          "bio": "janis.txt"
      },
      {
          "id": "P118",
          "name": "Miriam",
          "lastName": "Jiménez Iriarte"
      },
      {
          "id": "P119",
          "name": "Sergio",
          "lastName": "Mars"
      },
      {
          "id": "P120",
          "name": "Roser",
          "lastName": "Vales"
      },
      {
          "id": "P121",
          "name": "Job",
          "lastName": "Peró"
      },
      {
          "id": "P122",
          "name": "Iria G.",
          "lastName": "Parente"
      },
      {
          "id": "P123",
          "name": "Selene M.",
          "lastName": "Pascual"
      },
      {
          "id": "P124",
          "name": "Enerio",
          "lastName": "Dima"
      },
      {
          "id": "P125",
          "name": "Pablo",
          "lastName": "Campos"
      },
      {
          "id": "P126",
          "name": "Elena",
          "lastName": "Lozano"
      },
      {
          "id": "P127",
          "name": "Diana P.",
          "lastName": "Morales"
      },
      {
          "id": "P128",
          "alias": "P. Djélí Clark"
      },
      {
          "id": "P129",
          "name": "Jesús",
          "lastName": "Moracho"
      },
      {
          "id": "P130",
          "name": "Jorge",
          "lastName": "Prinzo"
      },
      {
          "id": "P131",
          "name": "Javier",
          "lastName": "Fernández"
      },
      {
          "id": "P133",
          "name": "Blanca",
          "lastName": "Rodríguez"
      },
      {
          "id": "P134",
          "name": "Paula",
          "lastName": "Cánoves",
          "image": "pcanoves.jpg",
          "bio": "pcanoves.txt"
      },
      {
          "id": "P135",
          "name": "Gabriella",
          "lastName": "Campbell"
      },
      {
          "id": "P136",
          "name": "Miguel",
          "lastName": "San Gregorio"
      },
      {
          "id": "P137",
          "name": "Leticia",
          "lastName": "Saenz"
      },
      {
          "id": "P138",
          "name": "Derek",
          "lastName": "Kunsken"
      },
      {
          "id": "P139",
          "name": "Leticia",
          "lastName": "Lara",
          "image": "llara.png",
          "bio": "llara.txt"
      },
      {
          "id": "P140",
          "name": "Iliana",
          "lastName": "Vargas",
          "image": "ivargas.jpg",
          "bio": "ivargas.txt"
      },
      {
          "id": "P141",
          "name": "Thiago",
          "lastName": "Lee",
          "image": "tlee.jpg",
          "bio": "tlee.txt"
      },
      {
          "id": "P142",
          "name": "Poldark",
          "lastName": "Mego",
          "image": "pmego.jpg",
          "bio": "pmego.txt"
      },
      {
          "id": "P143",
          "name": "Leonardo",
          "lastName": "Espinoza",
          "image": "lspinoza.jpg",
          "bio": "lspinoza.txt"
      },
      {
          "id": "P144",
          "name": "Paula",
          "lastName": "Yagüez i López-Jurado"
      },
      {
          "id": "P145",
          "name": "Ana",
          "lastName": "Tapia"
      },
      {
          "id": "P146",
          "name": "Olga",
          "lastName": "López"
      },
      {
          "id": "P147",
          "name": "Covadonga",
          "lastName": "Martínez-Pola"
      },
      {
          "id": "P148",
          "name": "Rubén",
          "lastName": "Sánchez Trigos"
      },
      {
          "id": "P149",
          "name": "Shaila",
          "lastName": "Correa"
      },
      {
          "id": "P150",
          "name": "María",
          "lastName": "Pérez de San Román"
      },
      {
          "id": "P151",
          "name": "Fabián",
          "lastName": "Plaza"
      },
      {
          "id": "P152",
          "name": "Vicky",
          "lastName": "Hidalgo"
      },
      {
          "id": "P153",
          "name": "Natalia",
          "lastName": "Sánchez"
      },
      {
          "id": "P154",
          "name": "Marina",
          "lastName": "Tena Tena"
      },
      {
          "id": "P155",
          "name": "Israel",
          "lastName": "Alonso",
          "image": "ialonso.jpg"
      },
      {
          "id": "P156",
          "name": "Carla",
          "lastName": "Bataller Estruch",
          "image": "cbataller.jpg",
          "bio": "cbataller.txt"
      },
      {
          "id": "P157",
          "name": "Luis",
          "lastName": "Zurriaga",
          "image": "lzurriaga.jpg",
          "bio": "lzurriaga.txt"
      },
      {
          "id": "P158",
          "name": "Silvia M.",
          "lastName": "Díaz",
          "image": "sdiaz.png",
          "bio": "sdiaz.txt"
      },
      {
          "id": "P159",
          "name": "Paula",
          "lastName": "Aparicio Cejudo",
          "image": "paparicio.jpg",
          "bio": "paparicio.txt"
      },
      {
          "id": "P160",
          "name": "Darío",
          "lastName": "Méndez",
          "image": "dmendez.png",
          "bio": "dmendez.txt"
      },
      {
          "id": "P161",
          "name": "Marcos Rafael",
          "lastName": "Cañas"
      },
      {
          "id": "P162",
          "name": "Daniel",
          "lastName": "Izur"
      },
      {
          "id": "P163",
          "name": "Alister",
          "lastName": "Mairon"
      },
      {
          "id": "P164",
          "name": "Alicia",
          "lastName": "Gili"
      },
      {
          "id": "P165",
          "name": "Eleazar",
          "lastName": "Herrera"
      },
      {
          "id": "P166",
          "name": "Sofía",
          "lastName": "Barker"
      },
      {
          "id": "P167",
          "name": "Alberto",
          "lastName": "Martínez Carcedo"
      },
      {
          "id": "P168",
          "name": "Inés",
          "lastName": "Galiano"
      },
      {
          "id": "P169",
          "name": "Elena",
          "lastName": "Torró"
      },
      {
          "id": "P170",
          "name": "Juan Carlos",
          "lastName": "Corman"
      },
      {
          "id": "P171",
          "name": "Raquel",
          "lastName": "Arbeteta"
      },
      {
          "id": "P172",
          "name": "Pepe",
          "lastName": "Carabel"
      },
      {
          "id": "P173",
          "name": "Sergio",
          "lastName": "Mullor"
      },
      {
          "id": "P174",
          "name": "Juan J.",
          "lastName": "Aranda Jiménez"
      },
      {
          "id": "P175",
          "name": "Pau",
          "lastName": "Ferrón Gallegos"
      },
      {
          "id": "P176",
          "name": "Olga",
          "lastName": "Sanchís Terol"
      },
      {
          "id": "P177",
          "name": "Estíbaliz",
          "lastName": "Espinosa Río"
      },
      {
          "id": "P178",
          "name": "Javier",
          "lastName": "Gayo Santacecilia"
      },
      {
          "id": "P179",
          "name": "Uxía",
          "lastName": "Vales"
      },
      {
          "id": "P180",
          "name": "Almudena",
          "lastName": "Martínez"
      },
      {
          "id": "P181",
          "name": "Rebeca",
          "lastName": "Cardeñoso Viña"
      },
      {
          "id": "P182",
          "name": "Míriam",
          "lastName": "Álvarez Elvira"
      },
      {
          "id": "P183",
          "name": "Jennifer",
          "lastName": "Fuentes"
      },
      {
          "id": "P184",
          "name": "Ramón",
          "lastName": "Balcells"
      },
      {
          "id": "P185",
          "name": "Mariola",
          "lastName": "Juncal"
      },
      {
          "id": "P186",
          "name": "Iván",
          "lastName": "Mayayo"
      },
      {
          "id": "P187",
          "name": "A. R.",
          "lastName": "Medina"
      },
      {
          "id": "P188",
          "name": "May",
          "lastName": "López"
      },
      {
          "id": "P189",
          "name": "Eneko",
          "lastName": "Menica"
      },
      {
          "id": "P190",
          "name": "Laura",
          "lastName": "Huelin"
      },
      {
          "id": "P191",
          "name": "David",
          "lastName": "Luna"
      },
      {
          "id": "P192",
          "name": "Estrella",
          "lastName": "Rodríguez Martín"
      },
      {
          "id": "P193",
          "name": "Samuel",
          "lastName": "Viñolo Locubiche"
      },
      {
          "id": "P194",
          "name": "Daniel",
          "lastName": "Govantes Carrasco"
      },
      {
          "id": "P195",
          "name": "Rosa",
          "lastName": "Jiménez Morales"
      },
      {
          "id": "P196",
          "name": "Jose Jesús",
          "lastName": "García Rueda"
      },
      {
          "id": "P197",
          "name": "Marina",
          "lastName": "Vidal"
      },
      {
          "id": "P198",
          "name": "H.M.",
          "lastName": "Zubieta"
      },
      {
          "id": "P199",
          "name": "L.G.",
          "lastName": "Morgan"
      },
      {
          "id": "P200",
          "name": "Chabier",
          "lastName": "Nogueras Corral"
      },
      {
          "id": "P201",
          "name": "Josu ",
          "lastName": "Gómez"
      },
      {
          "id": "P202",
          "name": "Edith",
          "lastName": "del Campo"
      },
      {
          "id": "P203",
          "alias": "Madame Eloise"
      },
      {
          "id": "P204",
          "name": "Nacho",
          "lastName": "Agulló"
      },
      {
          "id": "P205",
          "name": "Salvador",
          "lastName": "Bayarri"
      },
      {
          "id": "P206",
          "name": "Nick",
          "lastName": "Wu"
      },
      {
          "id": "P207",
          "name": "Regina",
          "lastName": "Kanyu Wang"
      },
      {
          "id": "P208",
          "name": "Manu",
          "lastName": "Viciano"
      },
      {
          "id": "P209",
          "name": "Tamara",
          "lastName": "Tonetti"
      },
      {
          "id": "P210",
          "name": "Darío",
          "lastName": "Díaz Anzalone"
      },
      {
          "id": "P211",
          "name": "Juan Francisco",
          "lastName": "Troya"
      },
      {
          "id": "P212",
          "name": "Carlo",
          "lastName": "Gallucci"
      },
      {
          "id": "P213",
          "name": "Elena",
          "lastName": "Durán"
      },
      {
          "id": "P214",
          "name": "María Antonia",
          "lastName": "Martí Escayol"
      },
      {
          "id": "P215",
          "name": "Mario David",
          "lastName": "Cárdenas Cancio"
      },
      {
          "id": "P216",
          "name": "Laura",
          "lastName": "Huerga"
      },
      {
          "id": "P217",
          "name": "Víctor",
          "lastName": "Guez"
      },
      {
          "id": "P218",
          "name": "Cristina",
          "lastName": "Carou"
      },
      {
          "id": "P219",
          "name": "Bárbara",
          "lastName": "García"
      },
      {
          "id": "P220",
          "name": "Eva",
          "lastName": "Duncan"
      },
      {
          "id": "P221",
          "name": "Claudia",
          "lastName": "Andrade Ecchio"
      },
      {
          "id": "P222",
          "name": "Cristian",
          "lastName": "Arenós Rebolledo"
      },
      {
          "id": "P223",
          "name": "Rubén",
          "lastName": "Rodríguez Rísquez"
      },
      {
          "id": "P224",
          "name": "Cristina",
          "lastName": "García Trufero "
      },
      {
          "id": "P225",
          "name": "Maeva",
          "lastName": "Nieto Piñero "
      },
      {
          "id": "P226",
          "name": "Cristina",
          "lastName": "Ogando"
      },
      {
          "id": "P227",
          "name": "Alicia",
          "lastName": "Pérez Gil"
      },
      {
          "id": "P228",
          "name": "Aura",
          "lastName": "Blanco"
      },
      {
          "id": "P229",
          "name": "Sara",
          "lastName": "García Rizzotto "
      },
      {
          "id": "P230",
          "name": "Cristina",
          "lastName": "Mestre"
      },
      {
          "id": "P231",
          "name": "Meritxell ",
          "lastName": "Terrón"
      },
      {
          "id": "P232",
          "name": "Patricia",
          "lastName": "Macías García"
      }
  ]
